date_model/__init__.py
date_model/engine.py
date_model/language.py
date_model/parser.py
date_model/ranges.py
date_model/relative.py
date_model/utils.py
date_model-1.1.4.dist-info/METADATA
date_model-1.1.4.dist-info/WHEEL
date_model-1.1.4.dist-info/top_level.txt
date_model-1.1.4.dist-info/RECORD
