Metadata-Version: 2.4
Name: date-model
Version: 1.1.4
Summary: Universal Date Parsing Engine
Requires-Python: >=3.8
